{
  "seedVersion": "2026-06-15-cn-v3",
  "bankSize": 200,
  "drawCount": 5,
  "points": 5,
  "questions": [
    {
      "id": "lc_001",
      "title": "在校园出行中，关于绿色出行，哪种做法更低碳？",
      "options": [
        "独自开燃油车",
        "短距离频繁叫车",
        "让车辆长时间怠速",
        "步行或骑行"
      ],
      "answer": 3,
      "explain": "短距离步行或骑行几乎不产生直接碳排放，也能增加日常运动。"
    },
    {
      "id": "lc_002",
      "title": "遇到校园出行场景时，绿色出行最推荐的做法是什么？",
      "options": [
        "短距离频繁叫车",
        "让车辆长时间怠速",
        "步行或骑行",
        "独自开燃油车"
      ],
      "answer": 2,
      "explain": "短距离步行或骑行几乎不产生直接碳排放，也能增加日常运动。"
    },
    {
      "id": "lc_003",
      "title": "下列哪项属于绿色出行的正确行动？",
      "options": [
        "让车辆长时间怠速",
        "步行或骑行",
        "独自开燃油车",
        "短距离频繁叫车"
      ],
      "answer": 1,
      "explain": "短距离步行或骑行几乎不产生直接碳排放，也能增加日常运动。"
    },
    {
      "id": "lc_004",
      "title": "想减少校园出行中绿色出行相关的碳排放，优先选择哪一项？",
      "options": [
        "步行或骑行",
        "独自开燃油车",
        "短距离频繁叫车",
        "让车辆长时间怠速"
      ],
      "answer": 0,
      "explain": "短距离步行或骑行几乎不产生直接碳排放，也能增加日常运动。"
    },
    {
      "id": "lc_005",
      "title": "在校园出行中，关于公共交通，哪种做法更低碳？",
      "options": [
        "每次都单人驾车",
        "为了方便空车绕行",
        "把车停在路边长时间开空调",
        "优先乘坐公交或地铁"
      ],
      "answer": 3,
      "explain": "公共交通能提高单次出行承载人数，分摊能源消耗。"
    },
    {
      "id": "lc_006",
      "title": "遇到校园出行场景时，公共交通最推荐的做法是什么？",
      "options": [
        "为了方便空车绕行",
        "把车停在路边长时间开空调",
        "优先乘坐公交或地铁",
        "每次都单人驾车"
      ],
      "answer": 2,
      "explain": "公共交通能提高单次出行承载人数，分摊能源消耗。"
    },
    {
      "id": "lc_007",
      "title": "下列哪项属于公共交通的正确行动？",
      "options": [
        "把车停在路边长时间开空调",
        "优先乘坐公交或地铁",
        "每次都单人驾车",
        "为了方便空车绕行"
      ],
      "answer": 1,
      "explain": "公共交通能提高单次出行承载人数，分摊能源消耗。"
    },
    {
      "id": "lc_008",
      "title": "想减少校园出行中公共交通相关的碳排放，优先选择哪一项？",
      "options": [
        "优先乘坐公交或地铁",
        "每次都单人驾车",
        "为了方便空车绕行",
        "把车停在路边长时间开空调"
      ],
      "answer": 0,
      "explain": "公共交通能提高单次出行承载人数，分摊能源消耗。"
    },
    {
      "id": "lc_009",
      "title": "在周末出行中，关于拼车出行，哪种做法更低碳？",
      "options": [
        "多人分别打车",
        "车辆空座也不共享",
        "为了凑里程绕远路",
        "同路线同学合理拼车"
      ],
      "answer": 3,
      "explain": "在确需乘车时，合理拼车可以减少重复车辆出行。"
    },
    {
      "id": "lc_010",
      "title": "遇到周末出行场景时，拼车出行最推荐的做法是什么？",
      "options": [
        "车辆空座也不共享",
        "为了凑里程绕远路",
        "同路线同学合理拼车",
        "多人分别打车"
      ],
      "answer": 2,
      "explain": "在确需乘车时，合理拼车可以减少重复车辆出行。"
    },
    {
      "id": "lc_011",
      "title": "下列哪项属于拼车出行的正确行动？",
      "options": [
        "为了凑里程绕远路",
        "同路线同学合理拼车",
        "多人分别打车",
        "车辆空座也不共享"
      ],
      "answer": 1,
      "explain": "在确需乘车时，合理拼车可以减少重复车辆出行。"
    },
    {
      "id": "lc_012",
      "title": "想减少周末出行中拼车出行相关的碳排放，优先选择哪一项？",
      "options": [
        "同路线同学合理拼车",
        "多人分别打车",
        "车辆空座也不共享",
        "为了凑里程绕远路"
      ],
      "answer": 0,
      "explain": "在确需乘车时，合理拼车可以减少重复车辆出行。"
    },
    {
      "id": "lc_013",
      "title": "在宿舍日常中，关于空调使用，哪种做法更低碳？",
      "options": [
        "温度越低越好",
        "开窗同时开空调",
        "离开房间不关闭",
        "夏季设置在二十六摄氏度左右"
      ],
      "answer": 3,
      "explain": "合理设置空调温度并关闭门窗，能明显减少电力消耗。"
    },
    {
      "id": "lc_014",
      "title": "遇到宿舍日常场景时，空调使用最推荐的做法是什么？",
      "options": [
        "开窗同时开空调",
        "离开房间不关闭",
        "夏季设置在二十六摄氏度左右",
        "温度越低越好"
      ],
      "answer": 2,
      "explain": "合理设置空调温度并关闭门窗，能明显减少电力消耗。"
    },
    {
      "id": "lc_015",
      "title": "下列哪项属于空调使用的正确行动？",
      "options": [
        "离开房间不关闭",
        "夏季设置在二十六摄氏度左右",
        "温度越低越好",
        "开窗同时开空调"
      ],
      "answer": 1,
      "explain": "合理设置空调温度并关闭门窗，能明显减少电力消耗。"
    },
    {
      "id": "lc_016",
      "title": "想减少宿舍日常中空调使用相关的碳排放，优先选择哪一项？",
      "options": [
        "夏季设置在二十六摄氏度左右",
        "温度越低越好",
        "开窗同时开空调",
        "离开房间不关闭"
      ],
      "answer": 0,
      "explain": "合理设置空调温度并关闭门窗，能明显减少电力消耗。"
    },
    {
      "id": "lc_017",
      "title": "在宿舍日常中，关于宿舍断电，哪种做法更低碳？",
      "options": [
        "只关一盏灯即可",
        "电脑一直待机",
        "充电器长期插在插座上",
        "离开前关闭电器并拔掉闲置插头"
      ],
      "answer": 3,
      "explain": "很多电器待机也会耗电，拔掉闲置插头更节能也更安全。"
    },
    {
      "id": "lc_018",
      "title": "遇到宿舍日常场景时，宿舍断电最推荐的做法是什么？",
      "options": [
        "电脑一直待机",
        "充电器长期插在插座上",
        "离开前关闭电器并拔掉闲置插头",
        "只关一盏灯即可"
      ],
      "answer": 2,
      "explain": "很多电器待机也会耗电，拔掉闲置插头更节能也更安全。"
    },
    {
      "id": "lc_019",
      "title": "下列哪项属于宿舍断电的正确行动？",
      "options": [
        "充电器长期插在插座上",
        "离开前关闭电器并拔掉闲置插头",
        "只关一盏灯即可",
        "电脑一直待机"
      ],
      "answer": 1,
      "explain": "很多电器待机也会耗电，拔掉闲置插头更节能也更安全。"
    },
    {
      "id": "lc_020",
      "title": "想减少宿舍日常中宿舍断电相关的碳排放，优先选择哪一项？",
      "options": [
        "离开前关闭电器并拔掉闲置插头",
        "只关一盏灯即可",
        "电脑一直待机",
        "充电器长期插在插座上"
      ],
      "answer": 0,
      "explain": "很多电器待机也会耗电，拔掉闲置插头更节能也更安全。"
    },
    {
      "id": "lc_021",
      "title": "在教学楼课间中，关于节能照明，哪种做法更低碳？",
      "options": [
        "白天也开满所有灯",
        "没人时保持照明",
        "用高耗能灯具替代节能灯",
        "使用节能灯并随手关灯"
      ],
      "answer": 3,
      "explain": "节能灯具和随手关灯是最容易坚持的低碳习惯。"
    },
    {
      "id": "lc_022",
      "title": "遇到教学楼课间场景时，节能照明最推荐的做法是什么？",
      "options": [
        "没人时保持照明",
        "用高耗能灯具替代节能灯",
        "使用节能灯并随手关灯",
        "白天也开满所有灯"
      ],
      "answer": 2,
      "explain": "节能灯具和随手关灯是最容易坚持的低碳习惯。"
    },
    {
      "id": "lc_023",
      "title": "下列哪项属于节能照明的正确行动？",
      "options": [
        "用高耗能灯具替代节能灯",
        "使用节能灯并随手关灯",
        "白天也开满所有灯",
        "没人时保持照明"
      ],
      "answer": 1,
      "explain": "节能灯具和随手关灯是最容易坚持的低碳习惯。"
    },
    {
      "id": "lc_024",
      "title": "想减少教学楼课间中节能照明相关的碳排放，优先选择哪一项？",
      "options": [
        "使用节能灯并随手关灯",
        "白天也开满所有灯",
        "没人时保持照明",
        "用高耗能灯具替代节能灯"
      ],
      "answer": 0,
      "explain": "节能灯具和随手关灯是最容易坚持的低碳习惯。"
    },
    {
      "id": "lc_025",
      "title": "在图书馆学习中，关于电脑节能，哪种做法更低碳？",
      "options": [
        "屏幕常亮一整天",
        "下载完也不关机",
        "多台设备同时闲置运行",
        "不用时启用睡眠或关机"
      ],
      "answer": 3,
      "explain": "电脑睡眠和关机能减少无效用电，延长设备寿命。"
    },
    {
      "id": "lc_026",
      "title": "遇到图书馆学习场景时，电脑节能最推荐的做法是什么？",
      "options": [
        "下载完也不关机",
        "多台设备同时闲置运行",
        "不用时启用睡眠或关机",
        "屏幕常亮一整天"
      ],
      "answer": 2,
      "explain": "电脑睡眠和关机能减少无效用电，延长设备寿命。"
    },
    {
      "id": "lc_027",
      "title": "下列哪项属于电脑节能的正确行动？",
      "options": [
        "多台设备同时闲置运行",
        "不用时启用睡眠或关机",
        "屏幕常亮一整天",
        "下载完也不关机"
      ],
      "answer": 1,
      "explain": "电脑睡眠和关机能减少无效用电，延长设备寿命。"
    },
    {
      "id": "lc_028",
      "title": "想减少图书馆学习中电脑节能相关的碳排放，优先选择哪一项？",
      "options": [
        "不用时启用睡眠或关机",
        "屏幕常亮一整天",
        "下载完也不关机",
        "多台设备同时闲置运行"
      ],
      "answer": 0,
      "explain": "电脑睡眠和关机能减少无效用电，延长设备寿命。"
    },
    {
      "id": "lc_029",
      "title": "在宿舍日常中，关于手机充电，哪种做法更低碳？",
      "options": [
        "整夜持续充电",
        "不用也插着充电头",
        "多个充电器长期空插",
        "充满后及时拔掉充电器"
      ],
      "answer": 3,
      "explain": "及时拔掉充电器可以降低待机能耗和安全风险。"
    },
    {
      "id": "lc_030",
      "title": "遇到宿舍日常场景时，手机充电最推荐的做法是什么？",
      "options": [
        "不用也插着充电头",
        "多个充电器长期空插",
        "充满后及时拔掉充电器",
        "整夜持续充电"
      ],
      "answer": 2,
      "explain": "及时拔掉充电器可以降低待机能耗和安全风险。"
    },
    {
      "id": "lc_031",
      "title": "下列哪项属于手机充电的正确行动？",
      "options": [
        "多个充电器长期空插",
        "充满后及时拔掉充电器",
        "整夜持续充电",
        "不用也插着充电头"
      ],
      "answer": 1,
      "explain": "及时拔掉充电器可以降低待机能耗和安全风险。"
    },
    {
      "id": "lc_032",
      "title": "想减少宿舍日常中手机充电相关的碳排放，优先选择哪一项？",
      "options": [
        "充满后及时拔掉充电器",
        "整夜持续充电",
        "不用也插着充电头",
        "多个充电器长期空插"
      ],
      "answer": 0,
      "explain": "及时拔掉充电器可以降低待机能耗和安全风险。"
    },
    {
      "id": "lc_033",
      "title": "在校园用水中，关于节约用水，哪种做法更低碳？",
      "options": [
        "水一直开着",
        "用大量清水反复冲洗",
        "发现滴漏不报修",
        "洗手打皂时关闭水龙头"
      ],
      "answer": 3,
      "explain": "随手关水和及时报修漏水点，是校园节水的基础行动。"
    },
    {
      "id": "lc_034",
      "title": "遇到校园用水场景时，节约用水最推荐的做法是什么？",
      "options": [
        "用大量清水反复冲洗",
        "发现滴漏不报修",
        "洗手打皂时关闭水龙头",
        "水一直开着"
      ],
      "answer": 2,
      "explain": "随手关水和及时报修漏水点，是校园节水的基础行动。"
    },
    {
      "id": "lc_035",
      "title": "下列哪项属于节约用水的正确行动？",
      "options": [
        "发现滴漏不报修",
        "洗手打皂时关闭水龙头",
        "水一直开着",
        "用大量清水反复冲洗"
      ],
      "answer": 1,
      "explain": "随手关水和及时报修漏水点，是校园节水的基础行动。"
    },
    {
      "id": "lc_036",
      "title": "想减少校园用水中节约用水相关的碳排放，优先选择哪一项？",
      "options": [
        "洗手打皂时关闭水龙头",
        "水一直开着",
        "用大量清水反复冲洗",
        "发现滴漏不报修"
      ],
      "answer": 0,
      "explain": "随手关水和及时报修漏水点，是校园节水的基础行动。"
    },
    {
      "id": "lc_037",
      "title": "在校园用水中，关于一水多用，哪种做法更低碳？",
      "options": [
        "少量可用水直接倒掉",
        "把污水倒入绿地",
        "用饮用水冲洗地面",
        "能回收的清水用于拖地或浇花"
      ],
      "answer": 3,
      "explain": "一水多用能提高水资源利用效率，但要注意水质和卫生。"
    },
    {
      "id": "lc_038",
      "title": "遇到校园用水场景时，一水多用最推荐的做法是什么？",
      "options": [
        "把污水倒入绿地",
        "用饮用水冲洗地面",
        "能回收的清水用于拖地或浇花",
        "少量可用水直接倒掉"
      ],
      "answer": 2,
      "explain": "一水多用能提高水资源利用效率，但要注意水质和卫生。"
    },
    {
      "id": "lc_039",
      "title": "下列哪项属于一水多用的正确行动？",
      "options": [
        "用饮用水冲洗地面",
        "能回收的清水用于拖地或浇花",
        "少量可用水直接倒掉",
        "把污水倒入绿地"
      ],
      "answer": 1,
      "explain": "一水多用能提高水资源利用效率，但要注意水质和卫生。"
    },
    {
      "id": "lc_040",
      "title": "想减少校园用水中一水多用相关的碳排放，优先选择哪一项？",
      "options": [
        "能回收的清水用于拖地或浇花",
        "少量可用水直接倒掉",
        "把污水倒入绿地",
        "用饮用水冲洗地面"
      ],
      "answer": 0,
      "explain": "一水多用能提高水资源利用效率，但要注意水质和卫生。"
    },
    {
      "id": "lc_041",
      "title": "在垃圾分类中，关于可回收物，哪种做法更低碳？",
      "options": [
        "和剩饭一起丢",
        "随手扔进任意垃圾桶",
        "把有害垃圾混进去",
        "干净纸张和塑料瓶投入可回收物桶"
      ],
      "answer": 3,
      "explain": "可回收物保持清洁干燥，更利于后续回收利用。"
    },
    {
      "id": "lc_042",
      "title": "遇到垃圾分类场景时，可回收物最推荐的做法是什么？",
      "options": [
        "随手扔进任意垃圾桶",
        "把有害垃圾混进去",
        "干净纸张和塑料瓶投入可回收物桶",
        "和剩饭一起丢"
      ],
      "answer": 2,
      "explain": "可回收物保持清洁干燥，更利于后续回收利用。"
    },
    {
      "id": "lc_043",
      "title": "下列哪项属于可回收物的正确行动？",
      "options": [
        "把有害垃圾混进去",
        "干净纸张和塑料瓶投入可回收物桶",
        "和剩饭一起丢",
        "随手扔进任意垃圾桶"
      ],
      "answer": 1,
      "explain": "可回收物保持清洁干燥，更利于后续回收利用。"
    },
    {
      "id": "lc_044",
      "title": "想减少垃圾分类中可回收物相关的碳排放，优先选择哪一项？",
      "options": [
        "干净纸张和塑料瓶投入可回收物桶",
        "和剩饭一起丢",
        "随手扔进任意垃圾桶",
        "把有害垃圾混进去"
      ],
      "answer": 0,
      "explain": "可回收物保持清洁干燥，更利于后续回收利用。"
    },
    {
      "id": "lc_045",
      "title": "在食堂就餐中，关于厨余垃圾，哪种做法更低碳？",
      "options": [
        "和纸杯混在一起",
        "倒进可回收物桶",
        "随意留在餐桌上",
        "剩饭剩菜投入厨余垃圾桶"
      ],
      "answer": 3,
      "explain": "厨余垃圾单独投放，有助于资源化处理和环境卫生。"
    },
    {
      "id": "lc_046",
      "title": "遇到食堂就餐场景时，厨余垃圾最推荐的做法是什么？",
      "options": [
        "倒进可回收物桶",
        "随意留在餐桌上",
        "剩饭剩菜投入厨余垃圾桶",
        "和纸杯混在一起"
      ],
      "answer": 2,
      "explain": "厨余垃圾单独投放，有助于资源化处理和环境卫生。"
    },
    {
      "id": "lc_047",
      "title": "下列哪项属于厨余垃圾的正确行动？",
      "options": [
        "随意留在餐桌上",
        "剩饭剩菜投入厨余垃圾桶",
        "和纸杯混在一起",
        "倒进可回收物桶"
      ],
      "answer": 1,
      "explain": "厨余垃圾单独投放，有助于资源化处理和环境卫生。"
    },
    {
      "id": "lc_048",
      "title": "想减少食堂就餐中厨余垃圾相关的碳排放，优先选择哪一项？",
      "options": [
        "剩饭剩菜投入厨余垃圾桶",
        "和纸杯混在一起",
        "倒进可回收物桶",
        "随意留在餐桌上"
      ],
      "answer": 0,
      "explain": "厨余垃圾单独投放，有助于资源化处理和环境卫生。"
    },
    {
      "id": "lc_049",
      "title": "在垃圾分类中，关于有害垃圾，哪种做法更低碳？",
      "options": [
        "混入普通垃圾",
        "丢进草坪",
        "拆开后随意丢弃",
        "废电池和过期药品投放到有害垃圾点"
      ],
      "answer": 3,
      "explain": "有害垃圾需要专门处理，避免污染土壤和水体。"
    },
    {
      "id": "lc_050",
      "title": "遇到垃圾分类场景时，有害垃圾最推荐的做法是什么？",
      "options": [
        "丢进草坪",
        "拆开后随意丢弃",
        "废电池和过期药品投放到有害垃圾点",
        "混入普通垃圾"
      ],
      "answer": 2,
      "explain": "有害垃圾需要专门处理，避免污染土壤和水体。"
    },
    {
      "id": "lc_051",
      "title": "下列哪项属于有害垃圾的正确行动？",
      "options": [
        "拆开后随意丢弃",
        "废电池和过期药品投放到有害垃圾点",
        "混入普通垃圾",
        "丢进草坪"
      ],
      "answer": 1,
      "explain": "有害垃圾需要专门处理，避免污染土壤和水体。"
    },
    {
      "id": "lc_052",
      "title": "想减少垃圾分类中有害垃圾相关的碳排放，优先选择哪一项？",
      "options": [
        "废电池和过期药品投放到有害垃圾点",
        "混入普通垃圾",
        "丢进草坪",
        "拆开后随意丢弃"
      ],
      "answer": 0,
      "explain": "有害垃圾需要专门处理，避免污染土壤和水体。"
    },
    {
      "id": "lc_053",
      "title": "在垃圾分类中，关于其他垃圾，哪种做法更低碳？",
      "options": [
        "都投可回收物桶",
        "都投厨余垃圾桶",
        "随意堆在楼道",
        "污染严重且不可回收的物品投其他垃圾"
      ],
      "answer": 3,
      "explain": "无法回收且不属于厨余、有害的垃圾，通常按其他垃圾处理。"
    },
    {
      "id": "lc_054",
      "title": "遇到垃圾分类场景时，其他垃圾最推荐的做法是什么？",
      "options": [
        "都投厨余垃圾桶",
        "随意堆在楼道",
        "污染严重且不可回收的物品投其他垃圾",
        "都投可回收物桶"
      ],
      "answer": 2,
      "explain": "无法回收且不属于厨余、有害的垃圾，通常按其他垃圾处理。"
    },
    {
      "id": "lc_055",
      "title": "下列哪项属于其他垃圾的正确行动？",
      "options": [
        "随意堆在楼道",
        "污染严重且不可回收的物品投其他垃圾",
        "都投可回收物桶",
        "都投厨余垃圾桶"
      ],
      "answer": 1,
      "explain": "无法回收且不属于厨余、有害的垃圾，通常按其他垃圾处理。"
    },
    {
      "id": "lc_056",
      "title": "想减少垃圾分类中其他垃圾相关的碳排放，优先选择哪一项？",
      "options": [
        "污染严重且不可回收的物品投其他垃圾",
        "都投可回收物桶",
        "都投厨余垃圾桶",
        "随意堆在楼道"
      ],
      "answer": 0,
      "explain": "无法回收且不属于厨余、有害的垃圾，通常按其他垃圾处理。"
    },
    {
      "id": "lc_057",
      "title": "在食堂就餐中，关于光盘行动，哪种做法更低碳？",
      "options": [
        "先多拿再说",
        "只拍照不吃完",
        "剩饭直接留在桌上",
        "按需取餐并尽量吃完"
      ],
      "answer": 3,
      "explain": "减少食物浪费能降低食物生产、运输和处理过程中的碳排放。"
    },
    {
      "id": "lc_058",
      "title": "遇到食堂就餐场景时，光盘行动最推荐的做法是什么？",
      "options": [
        "只拍照不吃完",
        "剩饭直接留在桌上",
        "按需取餐并尽量吃完",
        "先多拿再说"
      ],
      "answer": 2,
      "explain": "减少食物浪费能降低食物生产、运输和处理过程中的碳排放。"
    },
    {
      "id": "lc_059",
      "title": "下列哪项属于光盘行动的正确行动？",
      "options": [
        "剩饭直接留在桌上",
        "按需取餐并尽量吃完",
        "先多拿再说",
        "只拍照不吃完"
      ],
      "answer": 1,
      "explain": "减少食物浪费能降低食物生产、运输和处理过程中的碳排放。"
    },
    {
      "id": "lc_060",
      "title": "想减少食堂就餐中光盘行动相关的碳排放，优先选择哪一项？",
      "options": [
        "按需取餐并尽量吃完",
        "先多拿再说",
        "只拍照不吃完",
        "剩饭直接留在桌上"
      ],
      "answer": 0,
      "explain": "减少食物浪费能降低食物生产、运输和处理过程中的碳排放。"
    },
    {
      "id": "lc_061",
      "title": "在食堂就餐中，关于食堂取餐，哪种做法更低碳？",
      "options": [
        "一次装满再丢掉",
        "为了排面多点很多菜",
        "不喜欢就整份倒掉",
        "少量多次取餐"
      ],
      "answer": 3,
      "explain": "少量多次更容易控制食量，也能减少浪费。"
    },
    {
      "id": "lc_062",
      "title": "遇到食堂就餐场景时，食堂取餐最推荐的做法是什么？",
      "options": [
        "为了排面多点很多菜",
        "不喜欢就整份倒掉",
        "少量多次取餐",
        "一次装满再丢掉"
      ],
      "answer": 2,
      "explain": "少量多次更容易控制食量，也能减少浪费。"
    },
    {
      "id": "lc_063",
      "title": "下列哪项属于食堂取餐的正确行动？",
      "options": [
        "不喜欢就整份倒掉",
        "少量多次取餐",
        "一次装满再丢掉",
        "为了排面多点很多菜"
      ],
      "answer": 1,
      "explain": "少量多次更容易控制食量，也能减少浪费。"
    },
    {
      "id": "lc_064",
      "title": "想减少食堂就餐中食堂取餐相关的碳排放，优先选择哪一项？",
      "options": [
        "少量多次取餐",
        "一次装满再丢掉",
        "为了排面多点很多菜",
        "不喜欢就整份倒掉"
      ],
      "answer": 0,
      "explain": "少量多次更容易控制食量，也能减少浪费。"
    },
    {
      "id": "lc_065",
      "title": "在食堂就餐中，关于一次性餐具，哪种做法更低碳？",
      "options": [
        "每餐都拿多套餐具",
        "餐具未用就丢弃",
        "优先选择一次性用品",
        "自带餐具或选择可重复使用餐具"
      ],
      "answer": 3,
      "explain": "减少一次性用品，可以减少原料消耗和垃圾产生。"
    },
    {
      "id": "lc_066",
      "title": "遇到食堂就餐场景时，一次性餐具最推荐的做法是什么？",
      "options": [
        "餐具未用就丢弃",
        "优先选择一次性用品",
        "自带餐具或选择可重复使用餐具",
        "每餐都拿多套餐具"
      ],
      "answer": 2,
      "explain": "减少一次性用品，可以减少原料消耗和垃圾产生。"
    },
    {
      "id": "lc_067",
      "title": "下列哪项属于一次性餐具的正确行动？",
      "options": [
        "优先选择一次性用品",
        "自带餐具或选择可重复使用餐具",
        "每餐都拿多套餐具",
        "餐具未用就丢弃"
      ],
      "answer": 1,
      "explain": "减少一次性用品，可以减少原料消耗和垃圾产生。"
    },
    {
      "id": "lc_068",
      "title": "想减少食堂就餐中一次性餐具相关的碳排放，优先选择哪一项？",
      "options": [
        "自带餐具或选择可重复使用餐具",
        "每餐都拿多套餐具",
        "餐具未用就丢弃",
        "优先选择一次性用品"
      ],
      "answer": 0,
      "explain": "减少一次性用品，可以减少原料消耗和垃圾产生。"
    },
    {
      "id": "lc_069",
      "title": "在校园饮水中，关于自带水杯，哪种做法更低碳？",
      "options": [
        "每天购买多瓶瓶装水",
        "一次性纸杯用完就丢",
        "水杯脏了就换新的",
        "使用自己的水杯接水"
      ],
      "answer": 3,
      "explain": "自带水杯能减少瓶装水和一次性杯子的使用。"
    },
    {
      "id": "lc_070",
      "title": "遇到校园饮水场景时，自带水杯最推荐的做法是什么？",
      "options": [
        "一次性纸杯用完就丢",
        "水杯脏了就换新的",
        "使用自己的水杯接水",
        "每天购买多瓶瓶装水"
      ],
      "answer": 2,
      "explain": "自带水杯能减少瓶装水和一次性杯子的使用。"
    },
    {
      "id": "lc_071",
      "title": "下列哪项属于自带水杯的正确行动？",
      "options": [
        "水杯脏了就换新的",
        "使用自己的水杯接水",
        "每天购买多瓶瓶装水",
        "一次性纸杯用完就丢"
      ],
      "answer": 1,
      "explain": "自带水杯能减少瓶装水和一次性杯子的使用。"
    },
    {
      "id": "lc_072",
      "title": "想减少校园饮水中自带水杯相关的碳排放，优先选择哪一项？",
      "options": [
        "使用自己的水杯接水",
        "每天购买多瓶瓶装水",
        "一次性纸杯用完就丢",
        "水杯脏了就换新的"
      ],
      "answer": 0,
      "explain": "自带水杯能减少瓶装水和一次性杯子的使用。"
    },
    {
      "id": "lc_073",
      "title": "在学习资料中，关于旧书流转，哪种做法更低碳？",
      "options": [
        "直接丢弃",
        "长期堆放发霉",
        "能用也撕掉",
        "把旧书捐赠、交换或二手流转"
      ],
      "answer": 3,
      "explain": "旧书继续使用，可以延长物品寿命并减少新书资源消耗。"
    },
    {
      "id": "lc_074",
      "title": "遇到学习资料场景时，旧书流转最推荐的做法是什么？",
      "options": [
        "长期堆放发霉",
        "能用也撕掉",
        "把旧书捐赠、交换或二手流转",
        "直接丢弃"
      ],
      "answer": 2,
      "explain": "旧书继续使用，可以延长物品寿命并减少新书资源消耗。"
    },
    {
      "id": "lc_075",
      "title": "下列哪项属于旧书流转的正确行动？",
      "options": [
        "能用也撕掉",
        "把旧书捐赠、交换或二手流转",
        "直接丢弃",
        "长期堆放发霉"
      ],
      "answer": 1,
      "explain": "旧书继续使用，可以延长物品寿命并减少新书资源消耗。"
    },
    {
      "id": "lc_076",
      "title": "想减少学习资料中旧书流转相关的碳排放，优先选择哪一项？",
      "options": [
        "把旧书捐赠、交换或二手流转",
        "直接丢弃",
        "长期堆放发霉",
        "能用也撕掉"
      ],
      "answer": 0,
      "explain": "旧书继续使用，可以延长物品寿命并减少新书资源消耗。"
    },
    {
      "id": "lc_077",
      "title": "在学习资料中，关于双面用纸，哪种做法更低碳？",
      "options": [
        "单面大量打印",
        "错一页就整本重打",
        "草稿纸只写一行就丢",
        "打印前选择双面打印"
      ],
      "answer": 3,
      "explain": "双面打印和草稿纸再利用能减少纸张消耗。"
    },
    {
      "id": "lc_078",
      "title": "遇到学习资料场景时，双面用纸最推荐的做法是什么？",
      "options": [
        "错一页就整本重打",
        "草稿纸只写一行就丢",
        "打印前选择双面打印",
        "单面大量打印"
      ],
      "answer": 2,
      "explain": "双面打印和草稿纸再利用能减少纸张消耗。"
    },
    {
      "id": "lc_079",
      "title": "下列哪项属于双面用纸的正确行动？",
      "options": [
        "草稿纸只写一行就丢",
        "打印前选择双面打印",
        "单面大量打印",
        "错一页就整本重打"
      ],
      "answer": 1,
      "explain": "双面打印和草稿纸再利用能减少纸张消耗。"
    },
    {
      "id": "lc_080",
      "title": "想减少学习资料中双面用纸相关的碳排放，优先选择哪一项？",
      "options": [
        "打印前选择双面打印",
        "单面大量打印",
        "错一页就整本重打",
        "草稿纸只写一行就丢"
      ],
      "answer": 0,
      "explain": "双面打印和草稿纸再利用能减少纸张消耗。"
    },
    {
      "id": "lc_081",
      "title": "在学习资料中，关于电子资料，哪种做法更低碳？",
      "options": [
        "所有资料都打印",
        "重复打印同一文件",
        "打印后不再使用",
        "能电子阅读时优先使用电子版"
      ],
      "answer": 3,
      "explain": "电子阅读适合通知、课件和临时材料，可减少不必要打印。"
    },
    {
      "id": "lc_082",
      "title": "遇到学习资料场景时，电子资料最推荐的做法是什么？",
      "options": [
        "重复打印同一文件",
        "打印后不再使用",
        "能电子阅读时优先使用电子版",
        "所有资料都打印"
      ],
      "answer": 2,
      "explain": "电子阅读适合通知、课件和临时材料，可减少不必要打印。"
    },
    {
      "id": "lc_083",
      "title": "下列哪项属于电子资料的正确行动？",
      "options": [
        "打印后不再使用",
        "能电子阅读时优先使用电子版",
        "所有资料都打印",
        "重复打印同一文件"
      ],
      "answer": 1,
      "explain": "电子阅读适合通知、课件和临时材料，可减少不必要打印。"
    },
    {
      "id": "lc_084",
      "title": "想减少学习资料中电子资料相关的碳排放，优先选择哪一项？",
      "options": [
        "能电子阅读时优先使用电子版",
        "所有资料都打印",
        "重复打印同一文件",
        "打印后不再使用"
      ],
      "answer": 0,
      "explain": "电子阅读适合通知、课件和临时材料，可减少不必要打印。"
    },
    {
      "id": "lc_085",
      "title": "在快递收取中，关于快递包装，哪种做法更低碳？",
      "options": [
        "全部混入厨余垃圾",
        "纸箱完好也撕碎丢弃",
        "可复用包装直接扔掉",
        "拆包后分类回收纸箱和填充物"
      ],
      "answer": 3,
      "explain": "快递纸箱和缓冲材料复用或回收，可以减少包装浪费。"
    },
    {
      "id": "lc_086",
      "title": "遇到快递收取场景时，快递包装最推荐的做法是什么？",
      "options": [
        "纸箱完好也撕碎丢弃",
        "可复用包装直接扔掉",
        "拆包后分类回收纸箱和填充物",
        "全部混入厨余垃圾"
      ],
      "answer": 2,
      "explain": "快递纸箱和缓冲材料复用或回收，可以减少包装浪费。"
    },
    {
      "id": "lc_087",
      "title": "下列哪项属于快递包装的正确行动？",
      "options": [
        "可复用包装直接扔掉",
        "拆包后分类回收纸箱和填充物",
        "全部混入厨余垃圾",
        "纸箱完好也撕碎丢弃"
      ],
      "answer": 1,
      "explain": "快递纸箱和缓冲材料复用或回收，可以减少包装浪费。"
    },
    {
      "id": "lc_088",
      "title": "想减少快递收取中快递包装相关的碳排放，优先选择哪一项？",
      "options": [
        "拆包后分类回收纸箱和填充物",
        "全部混入厨余垃圾",
        "纸箱完好也撕碎丢弃",
        "可复用包装直接扔掉"
      ],
      "answer": 0,
      "explain": "快递纸箱和缓冲材料复用或回收，可以减少包装浪费。"
    },
    {
      "id": "lc_089",
      "title": "在校园消费中，关于环保购物袋，哪种做法更低碳？",
      "options": [
        "每次都拿新塑料袋",
        "买少量物品也套多层袋",
        "可重复袋用一次就扔",
        "购物时自带可重复使用的袋子"
      ],
      "answer": 3,
      "explain": "重复使用购物袋能减少塑料制品消耗。"
    },
    {
      "id": "lc_090",
      "title": "遇到校园消费场景时，环保购物袋最推荐的做法是什么？",
      "options": [
        "买少量物品也套多层袋",
        "可重复袋用一次就扔",
        "购物时自带可重复使用的袋子",
        "每次都拿新塑料袋"
      ],
      "answer": 2,
      "explain": "重复使用购物袋能减少塑料制品消耗。"
    },
    {
      "id": "lc_091",
      "title": "下列哪项属于环保购物袋的正确行动？",
      "options": [
        "可重复袋用一次就扔",
        "购物时自带可重复使用的袋子",
        "每次都拿新塑料袋",
        "买少量物品也套多层袋"
      ],
      "answer": 1,
      "explain": "重复使用购物袋能减少塑料制品消耗。"
    },
    {
      "id": "lc_092",
      "title": "想减少校园消费中环保购物袋相关的碳排放，优先选择哪一项？",
      "options": [
        "购物时自带可重复使用的袋子",
        "每次都拿新塑料袋",
        "买少量物品也套多层袋",
        "可重复袋用一次就扔"
      ],
      "answer": 0,
      "explain": "重复使用购物袋能减少塑料制品消耗。"
    },
    {
      "id": "lc_093",
      "title": "在校园消费中，关于旧衣处理，哪种做法更低碳？",
      "options": [
        "还能穿也直接丢",
        "随意焚烧",
        "混入厨余垃圾",
        "干净旧衣捐赠、改造或回收"
      ],
      "answer": 3,
      "explain": "旧衣循环利用能减少纺织品浪费和处理压力。"
    },
    {
      "id": "lc_094",
      "title": "遇到校园消费场景时，旧衣处理最推荐的做法是什么？",
      "options": [
        "随意焚烧",
        "混入厨余垃圾",
        "干净旧衣捐赠、改造或回收",
        "还能穿也直接丢"
      ],
      "answer": 2,
      "explain": "旧衣循环利用能减少纺织品浪费和处理压力。"
    },
    {
      "id": "lc_095",
      "title": "下列哪项属于旧衣处理的正确行动？",
      "options": [
        "混入厨余垃圾",
        "干净旧衣捐赠、改造或回收",
        "还能穿也直接丢",
        "随意焚烧"
      ],
      "answer": 1,
      "explain": "旧衣循环利用能减少纺织品浪费和处理压力。"
    },
    {
      "id": "lc_096",
      "title": "想减少校园消费中旧衣处理相关的碳排放，优先选择哪一项？",
      "options": [
        "干净旧衣捐赠、改造或回收",
        "还能穿也直接丢",
        "随意焚烧",
        "混入厨余垃圾"
      ],
      "answer": 0,
      "explain": "旧衣循环利用能减少纺织品浪费和处理压力。"
    },
    {
      "id": "lc_097",
      "title": "在校园消费中，关于二手交易，哪种做法更低碳？",
      "options": [
        "全都买新的",
        "闲置物品长期落灰",
        "能用物品直接报废",
        "闲置物品通过校园二手平台流转"
      ],
      "answer": 3,
      "explain": "二手流转让物品发挥更长价值，也减少新产品生产需求。"
    },
    {
      "id": "lc_098",
      "title": "遇到校园消费场景时，二手交易最推荐的做法是什么？",
      "options": [
        "闲置物品长期落灰",
        "能用物品直接报废",
        "闲置物品通过校园二手平台流转",
        "全都买新的"
      ],
      "answer": 2,
      "explain": "二手流转让物品发挥更长价值，也减少新产品生产需求。"
    },
    {
      "id": "lc_099",
      "title": "下列哪项属于二手交易的正确行动？",
      "options": [
        "能用物品直接报废",
        "闲置物品通过校园二手平台流转",
        "全都买新的",
        "闲置物品长期落灰"
      ],
      "answer": 1,
      "explain": "二手流转让物品发挥更长价值，也减少新产品生产需求。"
    },
    {
      "id": "lc_100",
      "title": "想减少校园消费中二手交易相关的碳排放，优先选择哪一项？",
      "options": [
        "闲置物品通过校园二手平台流转",
        "全都买新的",
        "闲置物品长期落灰",
        "能用物品直接报废"
      ],
      "answer": 0,
      "explain": "二手流转让物品发挥更长价值，也减少新产品生产需求。"
    },
    {
      "id": "lc_101",
      "title": "在校园生态中，关于校园绿植，哪种做法更低碳？",
      "options": [
        "随意折枝",
        "踩踏绿地",
        "把垃圾埋进花坛",
        "爱护树木花草并参与养护"
      ],
      "answer": 3,
      "explain": "校园绿植有助于改善环境，也能提升大家的低碳意识。"
    },
    {
      "id": "lc_102",
      "title": "遇到校园生态场景时，校园绿植最推荐的做法是什么？",
      "options": [
        "踩踏绿地",
        "把垃圾埋进花坛",
        "爱护树木花草并参与养护",
        "随意折枝"
      ],
      "answer": 2,
      "explain": "校园绿植有助于改善环境，也能提升大家的低碳意识。"
    },
    {
      "id": "lc_103",
      "title": "下列哪项属于校园绿植的正确行动？",
      "options": [
        "把垃圾埋进花坛",
        "爱护树木花草并参与养护",
        "随意折枝",
        "踩踏绿地"
      ],
      "answer": 1,
      "explain": "校园绿植有助于改善环境，也能提升大家的低碳意识。"
    },
    {
      "id": "lc_104",
      "title": "想减少校园生态中校园绿植相关的碳排放，优先选择哪一项？",
      "options": [
        "爱护树木花草并参与养护",
        "随意折枝",
        "踩踏绿地",
        "把垃圾埋进花坛"
      ],
      "answer": 0,
      "explain": "校园绿植有助于改善环境，也能提升大家的低碳意识。"
    },
    {
      "id": "lc_105",
      "title": "在校园生态中，关于草坪保护，哪种做法更低碳？",
      "options": [
        "为了近路穿越草坪",
        "在草坪乱扔垃圾",
        "随意破坏绿化牌",
        "走规定道路不踩踏草坪"
      ],
      "answer": 3,
      "explain": "保护草坪能减少修复维护成本，维护校园生态环境。"
    },
    {
      "id": "lc_106",
      "title": "遇到校园生态场景时，草坪保护最推荐的做法是什么？",
      "options": [
        "在草坪乱扔垃圾",
        "随意破坏绿化牌",
        "走规定道路不踩踏草坪",
        "为了近路穿越草坪"
      ],
      "answer": 2,
      "explain": "保护草坪能减少修复维护成本，维护校园生态环境。"
    },
    {
      "id": "lc_107",
      "title": "下列哪项属于草坪保护的正确行动？",
      "options": [
        "随意破坏绿化牌",
        "走规定道路不踩踏草坪",
        "为了近路穿越草坪",
        "在草坪乱扔垃圾"
      ],
      "answer": 1,
      "explain": "保护草坪能减少修复维护成本，维护校园生态环境。"
    },
    {
      "id": "lc_108",
      "title": "想减少校园生态中草坪保护相关的碳排放，优先选择哪一项？",
      "options": [
        "走规定道路不踩踏草坪",
        "为了近路穿越草坪",
        "在草坪乱扔垃圾",
        "随意破坏绿化牌"
      ],
      "answer": 0,
      "explain": "保护草坪能减少修复维护成本，维护校园生态环境。"
    },
    {
      "id": "lc_109",
      "title": "在低碳认知中，关于碳足迹，哪种做法更低碳？",
      "options": [
        "只看价格不看消耗",
        "认为个人行为无影响",
        "把浪费当作正常现象",
        "记录出行、用电和消费产生的碳影响"
      ],
      "answer": 3,
      "explain": "了解碳足迹有助于发现可以改进的日常行为。"
    },
    {
      "id": "lc_110",
      "title": "遇到低碳认知场景时，碳足迹最推荐的做法是什么？",
      "options": [
        "认为个人行为无影响",
        "把浪费当作正常现象",
        "记录出行、用电和消费产生的碳影响",
        "只看价格不看消耗"
      ],
      "answer": 2,
      "explain": "了解碳足迹有助于发现可以改进的日常行为。"
    },
    {
      "id": "lc_111",
      "title": "下列哪项属于碳足迹的正确行动？",
      "options": [
        "把浪费当作正常现象",
        "记录出行、用电和消费产生的碳影响",
        "只看价格不看消耗",
        "认为个人行为无影响"
      ],
      "answer": 1,
      "explain": "了解碳足迹有助于发现可以改进的日常行为。"
    },
    {
      "id": "lc_112",
      "title": "想减少低碳认知中碳足迹相关的碳排放，优先选择哪一项？",
      "options": [
        "记录出行、用电和消费产生的碳影响",
        "只看价格不看消耗",
        "认为个人行为无影响",
        "把浪费当作正常现象"
      ],
      "answer": 0,
      "explain": "了解碳足迹有助于发现可以改进的日常行为。"
    },
    {
      "id": "lc_113",
      "title": "在低碳认知中，关于碳中和，哪种做法更低碳？",
      "options": [
        "只种树不减排",
        "排放越多越好",
        "和日常生活完全无关",
        "先减排，再通过碳汇等方式抵消剩余排放"
      ],
      "answer": 3,
      "explain": "碳中和强调减排优先，抵消是补充手段。"
    },
    {
      "id": "lc_114",
      "title": "遇到低碳认知场景时，碳中和最推荐的做法是什么？",
      "options": [
        "排放越多越好",
        "和日常生活完全无关",
        "先减排，再通过碳汇等方式抵消剩余排放",
        "只种树不减排"
      ],
      "answer": 2,
      "explain": "碳中和强调减排优先，抵消是补充手段。"
    },
    {
      "id": "lc_115",
      "title": "下列哪项属于碳中和的正确行动？",
      "options": [
        "和日常生活完全无关",
        "先减排，再通过碳汇等方式抵消剩余排放",
        "只种树不减排",
        "排放越多越好"
      ],
      "answer": 1,
      "explain": "碳中和强调减排优先，抵消是补充手段。"
    },
    {
      "id": "lc_116",
      "title": "想减少低碳认知中碳中和相关的碳排放，优先选择哪一项？",
      "options": [
        "先减排，再通过碳汇等方式抵消剩余排放",
        "只种树不减排",
        "排放越多越好",
        "和日常生活完全无关"
      ],
      "answer": 0,
      "explain": "碳中和强调减排优先，抵消是补充手段。"
    },
    {
      "id": "lc_117",
      "title": "在校园生态中，关于碳汇，哪种做法更低碳？",
      "options": [
        "一次性塑料越多碳汇越大",
        "开空调可以形成碳汇",
        "垃圾堆放就是碳汇",
        "森林、草地等生态系统吸收并固定二氧化碳"
      ],
      "answer": 3,
      "explain": "碳汇是生态系统吸收和储存碳的重要能力。"
    },
    {
      "id": "lc_118",
      "title": "遇到校园生态场景时，碳汇最推荐的做法是什么？",
      "options": [
        "开空调可以形成碳汇",
        "垃圾堆放就是碳汇",
        "森林、草地等生态系统吸收并固定二氧化碳",
        "一次性塑料越多碳汇越大"
      ],
      "answer": 2,
      "explain": "碳汇是生态系统吸收和储存碳的重要能力。"
    },
    {
      "id": "lc_119",
      "title": "下列哪项属于碳汇的正确行动？",
      "options": [
        "垃圾堆放就是碳汇",
        "森林、草地等生态系统吸收并固定二氧化碳",
        "一次性塑料越多碳汇越大",
        "开空调可以形成碳汇"
      ],
      "answer": 1,
      "explain": "碳汇是生态系统吸收和储存碳的重要能力。"
    },
    {
      "id": "lc_120",
      "title": "想减少校园生态中碳汇相关的碳排放，优先选择哪一项？",
      "options": [
        "森林、草地等生态系统吸收并固定二氧化碳",
        "一次性塑料越多碳汇越大",
        "开空调可以形成碳汇",
        "垃圾堆放就是碳汇"
      ],
      "answer": 0,
      "explain": "碳汇是生态系统吸收和储存碳的重要能力。"
    },
    {
      "id": "lc_121",
      "title": "在低碳认知中，关于新能源，哪种做法更低碳？",
      "options": [
        "优先浪费化石能源",
        "让设备空转耗电",
        "把节能设备闲置不用",
        "优先使用太阳能、风能等清洁能源"
      ],
      "answer": 3,
      "explain": "清洁能源能降低化石能源依赖，是低碳转型的重要方向。"
    },
    {
      "id": "lc_122",
      "title": "遇到低碳认知场景时，新能源最推荐的做法是什么？",
      "options": [
        "让设备空转耗电",
        "把节能设备闲置不用",
        "优先使用太阳能、风能等清洁能源",
        "优先浪费化石能源"
      ],
      "answer": 2,
      "explain": "清洁能源能降低化石能源依赖，是低碳转型的重要方向。"
    },
    {
      "id": "lc_123",
      "title": "下列哪项属于新能源的正确行动？",
      "options": [
        "把节能设备闲置不用",
        "优先使用太阳能、风能等清洁能源",
        "优先浪费化石能源",
        "让设备空转耗电"
      ],
      "answer": 1,
      "explain": "清洁能源能降低化石能源依赖，是低碳转型的重要方向。"
    },
    {
      "id": "lc_124",
      "title": "想减少低碳认知中新能源相关的碳排放，优先选择哪一项？",
      "options": [
        "优先使用太阳能、风能等清洁能源",
        "优先浪费化石能源",
        "让设备空转耗电",
        "把节能设备闲置不用"
      ],
      "answer": 0,
      "explain": "清洁能源能降低化石能源依赖，是低碳转型的重要方向。"
    },
    {
      "id": "lc_125",
      "title": "在校园建筑中，关于节能建筑，哪种做法更低碳？",
      "options": [
        "白天拉窗帘开灯",
        "门窗长期漏风不管",
        "冬夏都让空调满负荷运行",
        "利用自然采光和保温措施降低能耗"
      ],
      "answer": 3,
      "explain": "建筑节能需要采光、保温、通风和设备管理共同配合。"
    },
    {
      "id": "lc_126",
      "title": "遇到校园建筑场景时，节能建筑最推荐的做法是什么？",
      "options": [
        "门窗长期漏风不管",
        "冬夏都让空调满负荷运行",
        "利用自然采光和保温措施降低能耗",
        "白天拉窗帘开灯"
      ],
      "answer": 2,
      "explain": "建筑节能需要采光、保温、通风和设备管理共同配合。"
    },
    {
      "id": "lc_127",
      "title": "下列哪项属于节能建筑的正确行动？",
      "options": [
        "冬夏都让空调满负荷运行",
        "利用自然采光和保温措施降低能耗",
        "白天拉窗帘开灯",
        "门窗长期漏风不管"
      ],
      "answer": 1,
      "explain": "建筑节能需要采光、保温、通风和设备管理共同配合。"
    },
    {
      "id": "lc_128",
      "title": "想减少校园建筑中节能建筑相关的碳排放，优先选择哪一项？",
      "options": [
        "利用自然采光和保温措施降低能耗",
        "白天拉窗帘开灯",
        "门窗长期漏风不管",
        "冬夏都让空调满负荷运行"
      ],
      "answer": 0,
      "explain": "建筑节能需要采光、保温、通风和设备管理共同配合。"
    },
    {
      "id": "lc_129",
      "title": "在校园用水中，关于雨水收集，哪种做法更低碳？",
      "options": [
        "把雨水管堵住",
        "用饮用水替代所有浇灌水",
        "雨水直接污染后排放",
        "将可用雨水用于绿化浇灌"
      ],
      "answer": 3,
      "explain": "合理收集雨水能节约自来水，也有利于校园海绵设施运行。"
    },
    {
      "id": "lc_130",
      "title": "遇到校园用水场景时，雨水收集最推荐的做法是什么？",
      "options": [
        "用饮用水替代所有浇灌水",
        "雨水直接污染后排放",
        "将可用雨水用于绿化浇灌",
        "把雨水管堵住"
      ],
      "answer": 2,
      "explain": "合理收集雨水能节约自来水，也有利于校园海绵设施运行。"
    },
    {
      "id": "lc_131",
      "title": "下列哪项属于雨水收集的正确行动？",
      "options": [
        "雨水直接污染后排放",
        "将可用雨水用于绿化浇灌",
        "把雨水管堵住",
        "用饮用水替代所有浇灌水"
      ],
      "answer": 1,
      "explain": "合理收集雨水能节约自来水，也有利于校园海绵设施运行。"
    },
    {
      "id": "lc_132",
      "title": "想减少校园用水中雨水收集相关的碳排放，优先选择哪一项？",
      "options": [
        "将可用雨水用于绿化浇灌",
        "把雨水管堵住",
        "用饮用水替代所有浇灌水",
        "雨水直接污染后排放"
      ],
      "answer": 0,
      "explain": "合理收集雨水能节约自来水，也有利于校园海绵设施运行。"
    },
    {
      "id": "lc_133",
      "title": "在校园用水中，关于海绵校园，哪种做法更低碳？",
      "options": [
        "所有地面都硬化",
        "堵塞排水沟",
        "破坏下凹绿地",
        "通过透水铺装和绿地滞蓄雨水"
      ],
      "answer": 3,
      "explain": "海绵校园能吸收、滞蓄和净化雨水，提升环境韧性。"
    },
    {
      "id": "lc_134",
      "title": "遇到校园用水场景时，海绵校园最推荐的做法是什么？",
      "options": [
        "堵塞排水沟",
        "破坏下凹绿地",
        "通过透水铺装和绿地滞蓄雨水",
        "所有地面都硬化"
      ],
      "answer": 2,
      "explain": "海绵校园能吸收、滞蓄和净化雨水，提升环境韧性。"
    },
    {
      "id": "lc_135",
      "title": "下列哪项属于海绵校园的正确行动？",
      "options": [
        "破坏下凹绿地",
        "通过透水铺装和绿地滞蓄雨水",
        "所有地面都硬化",
        "堵塞排水沟"
      ],
      "answer": 1,
      "explain": "海绵校园能吸收、滞蓄和净化雨水，提升环境韧性。"
    },
    {
      "id": "lc_136",
      "title": "想减少校园用水中海绵校园相关的碳排放，优先选择哪一项？",
      "options": [
        "通过透水铺装和绿地滞蓄雨水",
        "所有地面都硬化",
        "堵塞排水沟",
        "破坏下凹绿地"
      ],
      "answer": 0,
      "explain": "海绵校园能吸收、滞蓄和净化雨水，提升环境韧性。"
    },
    {
      "id": "lc_137",
      "title": "在校园消费中，关于绿色采购，哪种做法更低碳？",
      "options": [
        "只买一次性产品",
        "频繁更换还能用的物品",
        "忽视能效标识",
        "选择耐用、节能、可维修的产品"
      ],
      "answer": 3,
      "explain": "绿色采购关注全生命周期，耐用和节能都很重要。"
    },
    {
      "id": "lc_138",
      "title": "遇到校园消费场景时，绿色采购最推荐的做法是什么？",
      "options": [
        "频繁更换还能用的物品",
        "忽视能效标识",
        "选择耐用、节能、可维修的产品",
        "只买一次性产品"
      ],
      "answer": 2,
      "explain": "绿色采购关注全生命周期，耐用和节能都很重要。"
    },
    {
      "id": "lc_139",
      "title": "下列哪项属于绿色采购的正确行动？",
      "options": [
        "忽视能效标识",
        "选择耐用、节能、可维修的产品",
        "只买一次性产品",
        "频繁更换还能用的物品"
      ],
      "answer": 1,
      "explain": "绿色采购关注全生命周期，耐用和节能都很重要。"
    },
    {
      "id": "lc_140",
      "title": "想减少校园消费中绿色采购相关的碳排放，优先选择哪一项？",
      "options": [
        "选择耐用、节能、可维修的产品",
        "只买一次性产品",
        "频繁更换还能用的物品",
        "忽视能效标识"
      ],
      "answer": 0,
      "explain": "绿色采购关注全生命周期，耐用和节能都很重要。"
    },
    {
      "id": "lc_141",
      "title": "在社团活动中，关于低碳宣传，哪种做法更低碳？",
      "options": [
        "传播不实信息",
        "只喊口号不行动",
        "嘲笑他人的环保尝试",
        "用准确知识带动身边同学参与"
      ],
      "answer": 3,
      "explain": "低碳传播应真实、友善、可执行，才能形成持续影响。"
    },
    {
      "id": "lc_142",
      "title": "遇到社团活动场景时，低碳宣传最推荐的做法是什么？",
      "options": [
        "只喊口号不行动",
        "嘲笑他人的环保尝试",
        "用准确知识带动身边同学参与",
        "传播不实信息"
      ],
      "answer": 2,
      "explain": "低碳传播应真实、友善、可执行，才能形成持续影响。"
    },
    {
      "id": "lc_143",
      "title": "下列哪项属于低碳宣传的正确行动？",
      "options": [
        "嘲笑他人的环保尝试",
        "用准确知识带动身边同学参与",
        "传播不实信息",
        "只喊口号不行动"
      ],
      "answer": 1,
      "explain": "低碳传播应真实、友善、可执行，才能形成持续影响。"
    },
    {
      "id": "lc_144",
      "title": "想减少社团活动中低碳宣传相关的碳排放，优先选择哪一项？",
      "options": [
        "用准确知识带动身边同学参与",
        "传播不实信息",
        "只喊口号不行动",
        "嘲笑他人的环保尝试"
      ],
      "answer": 0,
      "explain": "低碳传播应真实、友善、可执行，才能形成持续影响。"
    },
    {
      "id": "lc_145",
      "title": "在校园活动中，关于活动布置，哪种做法更低碳？",
      "options": [
        "每次活动都全新购买",
        "活动后直接丢弃可用物料",
        "大量使用不可回收装饰",
        "重复使用展板、桌牌和装饰材料"
      ],
      "answer": 3,
      "explain": "校园活动物料复用能明显减少一次性消耗。"
    },
    {
      "id": "lc_146",
      "title": "遇到校园活动场景时，活动布置最推荐的做法是什么？",
      "options": [
        "活动后直接丢弃可用物料",
        "大量使用不可回收装饰",
        "重复使用展板、桌牌和装饰材料",
        "每次活动都全新购买"
      ],
      "answer": 2,
      "explain": "校园活动物料复用能明显减少一次性消耗。"
    },
    {
      "id": "lc_147",
      "title": "下列哪项属于活动布置的正确行动？",
      "options": [
        "大量使用不可回收装饰",
        "重复使用展板、桌牌和装饰材料",
        "每次活动都全新购买",
        "活动后直接丢弃可用物料"
      ],
      "answer": 1,
      "explain": "校园活动物料复用能明显减少一次性消耗。"
    },
    {
      "id": "lc_148",
      "title": "想减少校园活动中活动布置相关的碳排放，优先选择哪一项？",
      "options": [
        "重复使用展板、桌牌和装饰材料",
        "每次活动都全新购买",
        "活动后直接丢弃可用物料",
        "大量使用不可回收装饰"
      ],
      "answer": 0,
      "explain": "校园活动物料复用能明显减少一次性消耗。"
    },
    {
      "id": "lc_149",
      "title": "在校园会议中，关于会议节能，哪种做法更低碳？",
      "options": [
        "空房间长时间开灯",
        "每人多发几份纸质材料",
        "会议结束不关设备",
        "会前确认人数并减少纸质材料"
      ],
      "answer": 3,
      "explain": "会议管理中的用电、用纸和设备关闭都能节能。"
    },
    {
      "id": "lc_150",
      "title": "遇到校园会议场景时，会议节能最推荐的做法是什么？",
      "options": [
        "每人多发几份纸质材料",
        "会议结束不关设备",
        "会前确认人数并减少纸质材料",
        "空房间长时间开灯"
      ],
      "answer": 2,
      "explain": "会议管理中的用电、用纸和设备关闭都能节能。"
    },
    {
      "id": "lc_151",
      "title": "下列哪项属于会议节能的正确行动？",
      "options": [
        "会议结束不关设备",
        "会前确认人数并减少纸质材料",
        "空房间长时间开灯",
        "每人多发几份纸质材料"
      ],
      "answer": 1,
      "explain": "会议管理中的用电、用纸和设备关闭都能节能。"
    },
    {
      "id": "lc_152",
      "title": "想减少校园会议中会议节能相关的碳排放，优先选择哪一项？",
      "options": [
        "会前确认人数并减少纸质材料",
        "空房间长时间开灯",
        "每人多发几份纸质材料",
        "会议结束不关设备"
      ],
      "answer": 0,
      "explain": "会议管理中的用电、用纸和设备关闭都能节能。"
    },
    {
      "id": "lc_153",
      "title": "在实验实训中，关于实验室通风，哪种做法更低碳？",
      "options": [
        "无实验也一直开大风量",
        "随意关闭必要安全通风",
        "设备报警也不报修",
        "按安全要求使用通风并及时关闭不用设备"
      ],
      "answer": 3,
      "explain": "实验室低碳必须以安全为前提，避免无效运行。"
    },
    {
      "id": "lc_154",
      "title": "遇到实验实训场景时，实验室通风最推荐的做法是什么？",
      "options": [
        "随意关闭必要安全通风",
        "设备报警也不报修",
        "按安全要求使用通风并及时关闭不用设备",
        "无实验也一直开大风量"
      ],
      "answer": 2,
      "explain": "实验室低碳必须以安全为前提，避免无效运行。"
    },
    {
      "id": "lc_155",
      "title": "下列哪项属于实验室通风的正确行动？",
      "options": [
        "设备报警也不报修",
        "按安全要求使用通风并及时关闭不用设备",
        "无实验也一直开大风量",
        "随意关闭必要安全通风"
      ],
      "answer": 1,
      "explain": "实验室低碳必须以安全为前提，避免无效运行。"
    },
    {
      "id": "lc_156",
      "title": "想减少实验实训中实验室通风相关的碳排放，优先选择哪一项？",
      "options": [
        "按安全要求使用通风并及时关闭不用设备",
        "无实验也一直开大风量",
        "随意关闭必要安全通风",
        "设备报警也不报修"
      ],
      "answer": 0,
      "explain": "实验室低碳必须以安全为前提，避免无效运行。"
    },
    {
      "id": "lc_157",
      "title": "在实验实训中，关于实验废弃物，哪种做法更低碳？",
      "options": [
        "倒入普通垃圾桶",
        "随意倒进下水道",
        "混放不同危险废物",
        "按规定分类收集实验废弃物"
      ],
      "answer": 3,
      "explain": "实验废弃物需要规范处理，不能为了省事随意处置。"
    },
    {
      "id": "lc_158",
      "title": "遇到实验实训场景时，实验废弃物最推荐的做法是什么？",
      "options": [
        "随意倒进下水道",
        "混放不同危险废物",
        "按规定分类收集实验废弃物",
        "倒入普通垃圾桶"
      ],
      "answer": 2,
      "explain": "实验废弃物需要规范处理，不能为了省事随意处置。"
    },
    {
      "id": "lc_159",
      "title": "下列哪项属于实验废弃物的正确行动？",
      "options": [
        "混放不同危险废物",
        "按规定分类收集实验废弃物",
        "倒入普通垃圾桶",
        "随意倒进下水道"
      ],
      "answer": 1,
      "explain": "实验废弃物需要规范处理，不能为了省事随意处置。"
    },
    {
      "id": "lc_160",
      "title": "想减少实验实训中实验废弃物相关的碳排放，优先选择哪一项？",
      "options": [
        "按规定分类收集实验废弃物",
        "倒入普通垃圾桶",
        "随意倒进下水道",
        "混放不同危险废物"
      ],
      "answer": 0,
      "explain": "实验废弃物需要规范处理，不能为了省事随意处置。"
    },
    {
      "id": "lc_161",
      "title": "在学习资料中，关于打印习惯，哪种做法更低碳？",
      "options": [
        "不检查直接打印",
        "格式错了整份重打",
        "重复打印多个版本",
        "打印前预览并确认页数"
      ],
      "answer": 3,
      "explain": "打印预览能减少错印和重复打印造成的纸张浪费。"
    },
    {
      "id": "lc_162",
      "title": "遇到学习资料场景时，打印习惯最推荐的做法是什么？",
      "options": [
        "格式错了整份重打",
        "重复打印多个版本",
        "打印前预览并确认页数",
        "不检查直接打印"
      ],
      "answer": 2,
      "explain": "打印预览能减少错印和重复打印造成的纸张浪费。"
    },
    {
      "id": "lc_163",
      "title": "下列哪项属于打印习惯的正确行动？",
      "options": [
        "重复打印多个版本",
        "打印前预览并确认页数",
        "不检查直接打印",
        "格式错了整份重打"
      ],
      "answer": 1,
      "explain": "打印预览能减少错印和重复打印造成的纸张浪费。"
    },
    {
      "id": "lc_164",
      "title": "想减少学习资料中打印习惯相关的碳排放，优先选择哪一项？",
      "options": [
        "打印前预览并确认页数",
        "不检查直接打印",
        "格式错了整份重打",
        "重复打印多个版本"
      ],
      "answer": 0,
      "explain": "打印预览能减少错印和重复打印造成的纸张浪费。"
    },
    {
      "id": "lc_165",
      "title": "在教学楼课间中，关于楼层通行，哪种做法更低碳？",
      "options": [
        "一层也乘电梯",
        "电梯门反复空开",
        "多人分散占用多部电梯",
        "低楼层优先走楼梯"
      ],
      "answer": 3,
      "explain": "低楼层走楼梯既节能，也有利于身体活动。"
    },
    {
      "id": "lc_166",
      "title": "遇到教学楼课间场景时，楼层通行最推荐的做法是什么？",
      "options": [
        "电梯门反复空开",
        "多人分散占用多部电梯",
        "低楼层优先走楼梯",
        "一层也乘电梯"
      ],
      "answer": 2,
      "explain": "低楼层走楼梯既节能，也有利于身体活动。"
    },
    {
      "id": "lc_167",
      "title": "下列哪项属于楼层通行的正确行动？",
      "options": [
        "多人分散占用多部电梯",
        "低楼层优先走楼梯",
        "一层也乘电梯",
        "电梯门反复空开"
      ],
      "answer": 1,
      "explain": "低楼层走楼梯既节能，也有利于身体活动。"
    },
    {
      "id": "lc_168",
      "title": "想减少教学楼课间中楼层通行相关的碳排放，优先选择哪一项？",
      "options": [
        "低楼层优先走楼梯",
        "一层也乘电梯",
        "电梯门反复空开",
        "多人分散占用多部电梯"
      ],
      "answer": 0,
      "explain": "低楼层走楼梯既节能，也有利于身体活动。"
    },
    {
      "id": "lc_169",
      "title": "在宿舍日常中，关于洗衣晾晒，哪种做法更低碳？",
      "options": [
        "少量衣物多次机洗",
        "晴天也长时间烘干",
        "洗衣机空转",
        "衣物集中清洗并自然晾晒"
      ],
      "answer": 3,
      "explain": "集中洗衣和自然晾晒能减少水电消耗。"
    },
    {
      "id": "lc_170",
      "title": "遇到宿舍日常场景时，洗衣晾晒最推荐的做法是什么？",
      "options": [
        "晴天也长时间烘干",
        "洗衣机空转",
        "衣物集中清洗并自然晾晒",
        "少量衣物多次机洗"
      ],
      "answer": 2,
      "explain": "集中洗衣和自然晾晒能减少水电消耗。"
    },
    {
      "id": "lc_171",
      "title": "下列哪项属于洗衣晾晒的正确行动？",
      "options": [
        "洗衣机空转",
        "衣物集中清洗并自然晾晒",
        "少量衣物多次机洗",
        "晴天也长时间烘干"
      ],
      "answer": 1,
      "explain": "集中洗衣和自然晾晒能减少水电消耗。"
    },
    {
      "id": "lc_172",
      "title": "想减少宿舍日常中洗衣晾晒相关的碳排放，优先选择哪一项？",
      "options": [
        "衣物集中清洗并自然晾晒",
        "少量衣物多次机洗",
        "晴天也长时间烘干",
        "洗衣机空转"
      ],
      "answer": 0,
      "explain": "集中洗衣和自然晾晒能减少水电消耗。"
    },
    {
      "id": "lc_173",
      "title": "在食堂就餐中，关于外卖选择，哪种做法更低碳？",
      "options": [
        "每单都要多套餐具",
        "能堂食也频繁点外卖",
        "包装越复杂越好",
        "备注少餐具并选择简约包装"
      ],
      "answer": 3,
      "explain": "减少外卖餐具和过度包装，是日常低碳消费的一部分。"
    },
    {
      "id": "lc_174",
      "title": "遇到食堂就餐场景时，外卖选择最推荐的做法是什么？",
      "options": [
        "能堂食也频繁点外卖",
        "包装越复杂越好",
        "备注少餐具并选择简约包装",
        "每单都要多套餐具"
      ],
      "answer": 2,
      "explain": "减少外卖餐具和过度包装，是日常低碳消费的一部分。"
    },
    {
      "id": "lc_175",
      "title": "下列哪项属于外卖选择的正确行动？",
      "options": [
        "包装越复杂越好",
        "备注少餐具并选择简约包装",
        "每单都要多套餐具",
        "能堂食也频繁点外卖"
      ],
      "answer": 1,
      "explain": "减少外卖餐具和过度包装，是日常低碳消费的一部分。"
    },
    {
      "id": "lc_176",
      "title": "想减少食堂就餐中外卖选择相关的碳排放，优先选择哪一项？",
      "options": [
        "备注少餐具并选择简约包装",
        "每单都要多套餐具",
        "能堂食也频繁点外卖",
        "包装越复杂越好"
      ],
      "answer": 0,
      "explain": "减少外卖餐具和过度包装，是日常低碳消费的一部分。"
    },
    {
      "id": "lc_177",
      "title": "在食堂就餐中，关于饮食结构，哪种做法更低碳？",
      "options": [
        "每餐都大量浪费肉类",
        "只点不吃",
        "用高浪费方式备餐",
        "适量增加植物性食物比例"
      ],
      "answer": 3,
      "explain": "均衡饮食并减少浪费，有助于降低食物相关碳排放。"
    },
    {
      "id": "lc_178",
      "title": "遇到食堂就餐场景时，饮食结构最推荐的做法是什么？",
      "options": [
        "只点不吃",
        "用高浪费方式备餐",
        "适量增加植物性食物比例",
        "每餐都大量浪费肉类"
      ],
      "answer": 2,
      "explain": "均衡饮食并减少浪费，有助于降低食物相关碳排放。"
    },
    {
      "id": "lc_179",
      "title": "下列哪项属于饮食结构的正确行动？",
      "options": [
        "用高浪费方式备餐",
        "适量增加植物性食物比例",
        "每餐都大量浪费肉类",
        "只点不吃"
      ],
      "answer": 1,
      "explain": "均衡饮食并减少浪费，有助于降低食物相关碳排放。"
    },
    {
      "id": "lc_180",
      "title": "想减少食堂就餐中饮食结构相关的碳排放，优先选择哪一项？",
      "options": [
        "适量增加植物性食物比例",
        "每餐都大量浪费肉类",
        "只点不吃",
        "用高浪费方式备餐"
      ],
      "answer": 0,
      "explain": "均衡饮食并减少浪费，有助于降低食物相关碳排放。"
    },
    {
      "id": "lc_181",
      "title": "在食堂就餐中，关于本地食物，哪种做法更低碳？",
      "options": [
        "追求长距离空运食物",
        "反季食材越多越好",
        "忽视运输和保鲜消耗",
        "优先选择本地、当季食材"
      ],
      "answer": 3,
      "explain": "本地当季食材通常运输和储存压力更小。"
    },
    {
      "id": "lc_182",
      "title": "遇到食堂就餐场景时，本地食物最推荐的做法是什么？",
      "options": [
        "反季食材越多越好",
        "忽视运输和保鲜消耗",
        "优先选择本地、当季食材",
        "追求长距离空运食物"
      ],
      "answer": 2,
      "explain": "本地当季食材通常运输和储存压力更小。"
    },
    {
      "id": "lc_183",
      "title": "下列哪项属于本地食物的正确行动？",
      "options": [
        "忽视运输和保鲜消耗",
        "优先选择本地、当季食材",
        "追求长距离空运食物",
        "反季食材越多越好"
      ],
      "answer": 1,
      "explain": "本地当季食材通常运输和储存压力更小。"
    },
    {
      "id": "lc_184",
      "title": "想减少食堂就餐中本地食物相关的碳排放，优先选择哪一项？",
      "options": [
        "优先选择本地、当季食材",
        "追求长距离空运食物",
        "反季食材越多越好",
        "忽视运输和保鲜消耗"
      ],
      "answer": 0,
      "explain": "本地当季食材通常运输和储存压力更小。"
    },
    {
      "id": "lc_185",
      "title": "在食堂就餐中，关于食物保存，哪种做法更低碳？",
      "options": [
        "买了不吃直到变质",
        "剩菜随意丢弃",
        "冰箱塞满后不整理",
        "合理保存剩余食物并及时食用"
      ],
      "answer": 3,
      "explain": "合理保存能减少食物浪费，也减少厨余处理压力。"
    },
    {
      "id": "lc_186",
      "title": "遇到食堂就餐场景时，食物保存最推荐的做法是什么？",
      "options": [
        "剩菜随意丢弃",
        "冰箱塞满后不整理",
        "合理保存剩余食物并及时食用",
        "买了不吃直到变质"
      ],
      "answer": 2,
      "explain": "合理保存能减少食物浪费，也减少厨余处理压力。"
    },
    {
      "id": "lc_187",
      "title": "下列哪项属于食物保存的正确行动？",
      "options": [
        "冰箱塞满后不整理",
        "合理保存剩余食物并及时食用",
        "买了不吃直到变质",
        "剩菜随意丢弃"
      ],
      "answer": 1,
      "explain": "合理保存能减少食物浪费，也减少厨余处理压力。"
    },
    {
      "id": "lc_188",
      "title": "想减少食堂就餐中食物保存相关的碳排放，优先选择哪一项？",
      "options": [
        "合理保存剩余食物并及时食用",
        "买了不吃直到变质",
        "剩菜随意丢弃",
        "冰箱塞满后不整理"
      ],
      "answer": 0,
      "explain": "合理保存能减少食物浪费，也减少厨余处理压力。"
    },
    {
      "id": "lc_189",
      "title": "在校园出行中，关于骑行安全，哪种做法更低碳？",
      "options": [
        "把车停在消防通道",
        "骑行时逆行抢道",
        "损坏车辆后不处理",
        "规范停放共享单车并佩戴必要防护"
      ],
      "answer": 3,
      "explain": "低碳出行也要安全有序，不能影响公共秩序。"
    },
    {
      "id": "lc_190",
      "title": "遇到校园出行场景时，骑行安全最推荐的做法是什么？",
      "options": [
        "骑行时逆行抢道",
        "损坏车辆后不处理",
        "规范停放共享单车并佩戴必要防护",
        "把车停在消防通道"
      ],
      "answer": 2,
      "explain": "低碳出行也要安全有序，不能影响公共秩序。"
    },
    {
      "id": "lc_191",
      "title": "下列哪项属于骑行安全的正确行动？",
      "options": [
        "损坏车辆后不处理",
        "规范停放共享单车并佩戴必要防护",
        "把车停在消防通道",
        "骑行时逆行抢道"
      ],
      "answer": 1,
      "explain": "低碳出行也要安全有序，不能影响公共秩序。"
    },
    {
      "id": "lc_192",
      "title": "想减少校园出行中骑行安全相关的碳排放，优先选择哪一项？",
      "options": [
        "规范停放共享单车并佩戴必要防护",
        "把车停在消防通道",
        "骑行时逆行抢道",
        "损坏车辆后不处理"
      ],
      "answer": 0,
      "explain": "低碳出行也要安全有序，不能影响公共秩序。"
    },
    {
      "id": "lc_193",
      "title": "在垃圾分类中，关于空瓶回收，哪种做法更低碳？",
      "options": [
        "带液体直接乱扔",
        "和厨余混在一起",
        "丢到草丛里",
        "喝完的饮料瓶清空后投入可回收物桶"
      ],
      "answer": 3,
      "explain": "空瓶清空后回收，更方便后续分拣和再利用。"
    },
    {
      "id": "lc_194",
      "title": "遇到垃圾分类场景时，空瓶回收最推荐的做法是什么？",
      "options": [
        "和厨余混在一起",
        "丢到草丛里",
        "喝完的饮料瓶清空后投入可回收物桶",
        "带液体直接乱扔"
      ],
      "answer": 2,
      "explain": "空瓶清空后回收，更方便后续分拣和再利用。"
    },
    {
      "id": "lc_195",
      "title": "下列哪项属于空瓶回收的正确行动？",
      "options": [
        "丢到草丛里",
        "喝完的饮料瓶清空后投入可回收物桶",
        "带液体直接乱扔",
        "和厨余混在一起"
      ],
      "answer": 1,
      "explain": "空瓶清空后回收，更方便后续分拣和再利用。"
    },
    {
      "id": "lc_196",
      "title": "想减少垃圾分类中空瓶回收相关的碳排放，优先选择哪一项？",
      "options": [
        "喝完的饮料瓶清空后投入可回收物桶",
        "带液体直接乱扔",
        "和厨余混在一起",
        "丢到草丛里"
      ],
      "answer": 0,
      "explain": "空瓶清空后回收，更方便后续分拣和再利用。"
    },
    {
      "id": "lc_197",
      "title": "在低碳行动中，关于绿色承诺，哪种做法更低碳？",
      "options": [
        "只在打卡时行动",
        "目标越空越好",
        "别人监督才行动",
        "把低碳目标拆成每天能做到的小行动"
      ],
      "answer": 3,
      "explain": "低碳行为贵在持续，具体的小行动更容易形成习惯。"
    },
    {
      "id": "lc_198",
      "title": "遇到低碳行动场景时，绿色承诺最推荐的做法是什么？",
      "options": [
        "目标越空越好",
        "别人监督才行动",
        "把低碳目标拆成每天能做到的小行动",
        "只在打卡时行动"
      ],
      "answer": 2,
      "explain": "低碳行为贵在持续，具体的小行动更容易形成习惯。"
    },
    {
      "id": "lc_199",
      "title": "下列哪项属于绿色承诺的正确行动？",
      "options": [
        "别人监督才行动",
        "把低碳目标拆成每天能做到的小行动",
        "只在打卡时行动",
        "目标越空越好"
      ],
      "answer": 1,
      "explain": "低碳行为贵在持续，具体的小行动更容易形成习惯。"
    },
    {
      "id": "lc_200",
      "title": "想减少低碳行动中绿色承诺相关的碳排放，优先选择哪一项？",
      "options": [
        "把低碳目标拆成每天能做到的小行动",
        "只在打卡时行动",
        "目标越空越好",
        "别人监督才行动"
      ],
      "answer": 0,
      "explain": "低碳行为贵在持续，具体的小行动更容易形成习惯。"
    }
  ]
}
